fret_torch/__init__.py
fret_torch-0.1.1.dist-info/LICENSE
fret_torch-0.1.1.dist-info/METADATA
fret_torch-0.1.1.dist-info/WHEEL
fret_torch-0.1.1.dist-info/top_level.txt
fret_torch-0.1.1.dist-info/RECORD
